{"response": {"flightroute": {"callsign": "JBU620", "callsign_icao": "JBU620", "callsign_iata": "B6620", "airline": {"name": "JetBlue Airways", "icao": "JBU", "iata": "B6", "country": "United States", "country_iso": "US", "callsign": "JETBLUE"}, "origin": {"country_iso_name": "US", "country_name": "United States", "elevation": 17, "iata_code": "SAN", "icao_code": "KSAN", "latitude": 32.7336006165, "longitude": -117.190002441, "municipality": "San Diego", "name": "San Diego International Airport"}, "destination": {"country_iso_name": "US", "country_name": "United States", "elevation": 20, "iata_code": "BOS", "icao_code": "KBOS", "latitude": 42.3643, "longitude": -71.005203, "municipality": "Boston", "name": "Logan International Airport"}}}}