{"response": {"flightroute": {"callsign": "LOT1TE", "callsign_icao": "LOT1TE", "callsign_iata": "LO1TE", "airline": {"name": "LOT Polish Airlines", "icao": "LOT", "iata": "LO", "country": "Poland", "country_iso": "PL", "callsign": "POLLOT"}, "origin": {"country_iso_name": "US", "country_name": "United States", "elevation": 672, "iata_code": "ORD", "icao_code": "KORD", "latitude": 41.9786, "longitude": -87.9048, "municipality": "Chicago", "name": "Chicago O'Hare International Airport"}, "destination": {"country_iso_name": "PL", "country_name": "Poland", "elevation": 791, "iata_code": "KRK", "icao_code": "EPKK", "latitude": 50.077702, "longitude": 19.7848, "municipality": "Krak\u00f3w", "name": "Krak\u00f3w John Paul II International Airport"}}}}