{"response": {"flightroute": {"callsign": "SWA3431", "callsign_icao": "SWA3431", "callsign_iata": "WN3431", "airline": {"name": "Southwest Airlines", "icao": "SWA", "iata": "WN", "country": "United States", "country_iso": "US", "callsign": "SOUTHWEST"}, "origin": {"country_iso_name": "US", "country_name": "United States", "elevation": 487, "iata_code": "DAL", "icao_code": "KDAL", "latitude": 32.847099, "longitude": -96.851799, "municipality": "Dallas", "name": "Dallas Love Field"}, "destination": {"country_iso_name": "US", "country_name": "United States", "elevation": 4, "iata_code": "MSY", "icao_code": "KMSY", "latitude": 29.99340057373047, "longitude": -90.25800323486328, "municipality": "New Orleans", "name": "Louis Armstrong New Orleans International Airport"}}}}