{"response": {"flightroute": {"callsign": "UAL970", "callsign_icao": "UAL970", "callsign_iata": "UA970", "airline": {"name": "United Airlines", "icao": "UAL", "iata": "UA", "country": "United States", "country_iso": "US", "callsign": "UNITED"}, "origin": {"country_iso_name": "US", "country_name": "United States", "elevation": 672, "iata_code": "ORD", "icao_code": "KORD", "latitude": 41.9786, "longitude": -87.9048, "municipality": "Chicago", "name": "Chicago O'Hare International Airport"}, "destination": {"country_iso_name": "IT", "country_name": "Italy", "elevation": 13, "iata_code": "FCO", "icao_code": "LIRF", "latitude": 41.804532, "longitude": 12.251998, "municipality": "Rome", "name": "Rome\u2013Fiumicino Leonardo da Vinci International Airport"}}}}